tetris/__init__.py
tetris/__main__.py
tiny_tetris-0.0.0.dist-info/LICENSE
tiny_tetris-0.0.0.dist-info/METADATA
tiny_tetris-0.0.0.dist-info/WHEEL
tiny_tetris-0.0.0.dist-info/entry_points.txt
tiny_tetris-0.0.0.dist-info/RECORD
